LICENSE
MANIFEST.in
README.md
setup.cfg
setup.py
jsonrepo/__init__.py
jsonrepo/backend.py
jsonrepo/mixin.py
jsonrepo/record.py
jsonrepo/repository.py
jsonrepo/backends/__init__.py
jsonrepo/backends/dynamodb.py
jsonrepo/backends/memory.py
jsonrepo/backends/redis.py
python_jsonrepo.egg-info/PKG-INFO
python_jsonrepo.egg-info/SOURCES.txt
python_jsonrepo.egg-info/dependency_links.txt
python_jsonrepo.egg-info/requires.txt
python_jsonrepo.egg-info/top_level.txt
tests/__init__.py
tests/tests.py