Metadata-Version: 1.1
Name: python-jsonrepo
Version: 0.1.2
Summary: A simple repository for json serializable objects
Home-page: https://github.com/romaryd/python-jsonrepo
Author: Romary Dupuis
Author-email: romary@me.com
License: The MIT License (MIT)
